murmur/__init__.py
murmur/murmur.py
pymurmur-0.0.1.dist-info/licenses/LICENSE
pymurmur-0.0.1.dist-info/METADATA
pymurmur-0.0.1.dist-info/WHEEL
pymurmur-0.0.1.dist-info/top_level.txt
pymurmur-0.0.1.dist-info/RECORD
